setup.cfg
setup.py
fma/__init__.py
fma/antypes.py
fma/cfma.pyx
fma/collection.py
fma/connector.py
fma/const.py
fma/doclist.py
fma/exc.py
fma/helpers.py
fma/monga.py
fma/nested.py
fma/orm.py
fma/pendingop.py
fma/reg.py
fma/superdoc.py
fma/utils.py
fma.egg-info/PKG-INFO
fma.egg-info/SOURCES.txt
fma.egg-info/dependency_links.txt
fma.egg-info/not-zip-safe
fma.egg-info/requires.txt
fma.egg-info/top_level.txt
fma/tests/__init__.py
fma/tests/functional/__init__.py
fma/tests/functional/test_all.py