Metadata-Version: 1.0
Name: fma
Version: 0.0.15
Summary: Full Mongo Alchemyst
Home-page: http://www.mindtalk.com/u/anvie
Author: anvie
Author-email: r[@]nosql.asia
License: UNKNOWN
Download-URL: https://github.com/anvie/fullmongoalchemist
Keywords: fma mongo orm
Platform: UNKNOWN
